sopel_search/__init__.py
sopel_search/config.py
sopel_search/plugin.py
sopel_search-1.3.0.dist-info/licenses/COPYING
sopel_search-1.3.0.dist-info/METADATA
sopel_search-1.3.0.dist-info/WHEEL
sopel_search-1.3.0.dist-info/entry_points.txt
sopel_search-1.3.0.dist-info/top_level.txt
sopel_search-1.3.0.dist-info/RECORD
