Metadata-Version: 2.4
Name: sopel-search
Version: 1.3.0
Summary: Search plugin for Sopel IRC bots
Author-email: dgw <dgw@technobabbl.es>
License-Expression: EFL-2.0
Project-URL: Homepage, https://github.com/sopel-irc/sopel-search
Project-URL: Bug Tracker, https://github.com/sopel-irc/sopel-search/issues
Keywords: sopel,plugin,bot,irc
Platform: Linux x86, x86-64
Classifier: Intended Audience :: Developers
Classifier: Intended Audience :: System Administrators
Classifier: Programming Language :: Python :: 3 :: Only
Classifier: Topic :: Communications :: Chat :: Internet Relay Chat
Requires-Python: <4,>=3.9
License-File: COPYING
Requires-Dist: sopel>=8.0
Requires-Dist: ddgs>=9.0
Requires-Dist: xmltodict~=0.13.0
Requires-Dist: requests
Dynamic: license-file
